opaqueprompts/__init__.py
opaqueprompts/authentication.py
opaqueprompts/configuration.py
opaqueprompts/opaqueprompts_service.py
opaqueprompts-0.1.2.dist-info/LICENSE
opaqueprompts-0.1.2.dist-info/METADATA
opaqueprompts-0.1.2.dist-info/WHEEL
opaqueprompts-0.1.2.dist-info/top_level.txt
opaqueprompts-0.1.2.dist-info/RECORD
